qleet/__init__.py
qleet/_version.py
qleet/app.css
qleet/analyzers/__init__.py
qleet/analyzers/entanglement.py
qleet/analyzers/entanglement_spectrum.py
qleet/analyzers/expressibility.py
qleet/analyzers/histogram.py
qleet/analyzers/loss_landscape.py
qleet/analyzers/training_path.py
qleet/examples/__init__.py
qleet/examples/qaoa_maxcut.py
qleet/interface/__init__.py
qleet/interface/circuit.py
qleet/interface/dashboard.py
qleet/interface/metas.py
qleet/interface/metric_spec.py
qleet/simulators/__init__.py
qleet/simulators/circuit_simulators.py
qleet/simulators/pqc_trainer.py
qleet-0.2.0.2.dist-info/LICENSE
qleet-0.2.0.2.dist-info/WHEEL
qleet-0.2.0.2.dist-info/METADATA
qleet-0.2.0.2.dist-info/RECORD
