Metadata-Version: 2.1
Name: qleet
Version: 0.2.0.2
Summary: qLEET is an open-source library for exploring Loss landscape, Expressibility, Entangling capability and Training trajectories of noisy parameterized quantum circuits.
Keywords: NISQ,Quantum Computing,Quantum Programming
Author-email: Utkarsh Azad <utkarsh.azad@research.iiit.ac.in>, Animesh Sinha <animesh.sinha@research.iiit.ac.in>
Maintainer-email: QLemma <utkarshazad98@gmail.com>
Classifier: Development Status :: 4 - Beta
Classifier: Environment :: Console
Classifier: Intended Audience :: Science/Research
Classifier: License :: OSI Approved :: Apache Software License
Classifier: Natural Language :: English
Classifier: Operating System :: POSIX
Classifier: Operating System :: MacOS :: MacOS X
Classifier: Operating System :: POSIX :: Linux
Classifier: Operating System :: Microsoft :: Windows
Classifier: Programming Language :: Python
Classifier: Programming Language :: Python :: 3
Classifier: Programming Language :: Python :: 3.7
Classifier: Programming Language :: Python :: 3.8
Classifier: Programming Language :: Python :: 3.9
Classifier: Programming Language :: Python :: 3 :: Only
Classifier: Topic :: Scientific/Engineering :: Physics
Requires-Dist: cirq==0.11.0
Requires-Dist: sympy==1.5
Requires-Dist: tensorflow==2.4.1
Requires-Dist: tensorflow-quantum==0.5.1
Requires-Dist: numpy>=1.19
Requires-Dist: pandas>=1.3
Requires-Dist: tensorboard==2.5.0
Requires-Dist: qiskit==0.32.1
Requires-Dist: dash==1.21.0
Requires-Dist: networkx>=2.5
Requires-Dist: pandas>=1.1.0
Requires-Dist: plotly==5.1.0
Requires-Dist: scikit-learn==0.24.2
Requires-Dist: seaborn==0.11.1
Requires-Dist: tqdm==4.36.1
Requires-Dist: wandb
Requires-Dist: pylint==2.4.4
Requires-Dist: yapf==0.28.0
Requires-Dist: pyquil==2.28.1
Project-URL: Home, https://github.com/QLemma/qleet/
